wt_mqtt/__init__.py
wt_mqtt/wt_device_mqtt.py
wt_mqtt/wt_gateway_mqtt.py
wt_mqtt-2.0.1.dist-info/LICENSE
wt_mqtt-2.0.1.dist-info/METADATA
wt_mqtt-2.0.1.dist-info/WHEEL
wt_mqtt-2.0.1.dist-info/top_level.txt
wt_mqtt-2.0.1.dist-info/RECORD
