Metadata-Version: 2.1
Name: wt-mqtt
Version: 2.0.1
Summary: WaveletThings Python SDK
Home-page: UNKNOWN
Author: xiaoboplus
Author-email: xiaoboplus@waveletplus.com
License: UNKNOWN
Platform: UNKNOWN
Classifier: Programming Language :: Python :: 3
Classifier: License :: OSI Approved :: MIT License
Classifier: Operating System :: OS Independent
Requires-Python: >=3.6
License-File: LICENSE
Requires-Dist: jsonschema (>=3.2.0)
Requires-Dist: paho-mqtt (>=1.5.0)
